[
    { 
        "title": "How Selestial works?",
        "content": ""
    },
    { 
        "title": "What services do you offer?",
        "content": ""
    },
    { 
        "title": "Who’s behind Selestial?",
        "content": ""
    },
    { 
        "title": "How fast are requests completed?",
        "content": ""
    },
    { 
        "title": "Refunds Policy.",
        "content": ""
    },
    { 
        "title": "How much is a website?",
        "content": ""
    },
    { 
        "title": "How long does it take to make such awesome websites?",
        "content": ""
    },
    { 
        "title": "Can you also deal with bigger projects ?",
        "content": ""
    },
    { 
        "title": "Are you a designer or developer?",
        "content": ""
    },
    { 
        "title": "Is that really you in the framed picture above?",
        "content": ""
    },
    { 
        "title": "How do I become as awesome as you?",
        "content": ""
    },
    { 
        "title": "Did you use drugs while designing this website?",
        "content": ""
    },
    { 
        "title": "What is the content of the infamous hidden section?",
        "content": ""
    }
]